TODO.txt
bootstrap.py
buildout.cfg
setup.py
test-plone-2.5.cfg
test-plone-3.x.cfg
test-plone-4.x.cfg
Products/__init__.py
Products.salesforcebaseconnector.egg-info/PKG-INFO
Products.salesforcebaseconnector.egg-info/SOURCES.txt
Products.salesforcebaseconnector.egg-info/dependency_links.txt
Products.salesforcebaseconnector.egg-info/entry_points.txt
Products.salesforcebaseconnector.egg-info/namespace_packages.txt
Products.salesforcebaseconnector.egg-info/not-zip-safe
Products.salesforcebaseconnector.egg-info/requires.txt
Products.salesforcebaseconnector.egg-info/top_level.txt
Products/salesforcebaseconnector/CHANGES.txt
Products/salesforcebaseconnector/LICENSE.GPL
Products/salesforcebaseconnector/LICENSE.txt
Products/salesforcebaseconnector/README.txt
Products/salesforcebaseconnector/__init__.py
Products/salesforcebaseconnector/salesforcebaseconnector.py
Products/salesforcebaseconnector/utils.py
Products/salesforcebaseconnector/version.txt
Products/salesforcebaseconnector/interfaces/__init__.py
Products/salesforcebaseconnector/interfaces/salesforcebaseconnector.py
Products/salesforcebaseconnector/tests/__init__.py
Products/salesforcebaseconnector/tests/base.py
Products/salesforcebaseconnector/tests/layer.py
Products/salesforcebaseconnector/tests/sfconfig.py.in
Products/salesforcebaseconnector/tests/test_salesforcebaseconnector.py
Products/salesforcebaseconnector/tests/test_utils.py
Products/salesforcebaseconnector/www/manageAuthConfig.zpt
Products/salesforcebaseconnector/www/salesforce.png