Metadata-Version: 1.0
Name: Products.salesforcebaseconnector
Version: 1.4
Summary: Provides access to the Salesforce API within Zope 2, based on the beatbox library
Home-page: http://groups.google.com/group/plonesf
Author: Plone/Salesforce Integration Group
Author-email: plonesf@googlegroups.com
License: GPL
Keywords: Zope CMF Plone Salesforce.com CRM integration
Platform: UNKNOWN
Classifier: Programming Language :: Python
Classifier: Topic :: Software Development :: Libraries :: Python Modules
Classifier: Framework :: Zope2
Classifier: Development Status :: 5 - Production/Stable
